plexhints/__init__.py
plexhints/_helpers.py
plexhints/agent_kit.py
plexhints/const.py
plexhints/constant_kit.py
plexhints/core_kit.py
plexhints/decorator_kit.py
plexhints/exception_kit.py
plexhints/extras_kit.py
plexhints/locale_kit.py
plexhints/log_kit.py
plexhints/model_kit.py
plexhints/network_kit.py
plexhints/object_kit.py
plexhints/parse_kit.py
plexhints/plugin_kit.py
plexhints/prefs_kit.py
plexhints/proxy_kit.py
plexhints/resource_kit.py
plexhints/shortcut_kit.py
plexhints/template_kit.py
plexhints/util_kit.py
plexhints-2024.809.14117.data/data/README.rst
plexhints-2024.809.14117.data/data/requirements.txt
plexhints-2024.809.14117.data/data/docs/Makefile
plexhints-2024.809.14117.data/data/docs/build_plugin.rst
plexhints-2024.809.14117.data/data/docs/changelog.rst
plexhints-2024.809.14117.data/data/docs/conf.py
plexhints-2024.809.14117.data/data/docs/contributing.rst
plexhints-2024.809.14117.data/data/docs/github_action.rst
plexhints-2024.809.14117.data/data/docs/global.rst
plexhints-2024.809.14117.data/data/docs/index.rst
plexhints-2024.809.14117.data/data/docs/installation.rst
plexhints-2024.809.14117.data/data/docs/main.rst
plexhints-2024.809.14117.data/data/docs/make.bat
plexhints-2024.809.14117.data/data/docs/overview.rst
plexhints-2024.809.14117.data/data/docs/testing.rst
plexhints-2024.809.14117.data/data/docs/toc.rst
plexhints-2024.809.14117.data/data/docs/usage.rst
plexhints-2024.809.14117.dist-info/LICENSE
plexhints-2024.809.14117.dist-info/METADATA
plexhints-2024.809.14117.dist-info/WHEEL
plexhints-2024.809.14117.dist-info/top_level.txt
plexhints-2024.809.14117.dist-info/RECORD
