Metadata-Version: 2.1
Name: plexhints
Version: 2024.809.14117
Summary: Type hinting library for Plex plugin development.
Home-page: https://github.com/LizardByte/plexhints
Author: LizardByte
Author-email: LizardByte@github.com
License: UNKNOWN
Keywords: plex,agent,plug-in,debug
Platform: UNKNOWN
Classifier: Development Status :: 4 - Beta
Classifier: Intended Audience :: Developers
Classifier: License :: OSI Approved :: GNU Affero General Public License v3
Classifier: Operating System :: OS Independent
Classifier: Programming Language :: Python :: 2.7
Classifier: Programming Language :: Python :: 3.8
Classifier: Programming Language :: Python :: 3.9
Classifier: Programming Language :: Python :: 3.10
Classifier: Programming Language :: Python :: 3.11
Classifier: Topic :: Software Development :: Libraries :: Python Modules
Requires-Python: >=2.7
Requires-Dist: deprecation (==2.1.0)
Requires-Dist: future (==1.0.0)
Requires-Dist: simplejson (==3.19.2)
Requires-Dist: BeautifulSoup4 (==4.9.3) ; python_version < "3"
Requires-Dist: demjson (==2.2.4) ; python_version < "3"
Requires-Dist: feedparser (==5.2.1) ; python_version < "3"
Requires-Dist: lxml (==4.9.4) ; python_version < "3"
Requires-Dist: PyYAML (==5.4.1) ; python_version < "3"
Requires-Dist: requests (==2.27.1) ; python_version < "3"
Requires-Dist: requests-cache (==0.5.2) ; python_version < "3"
Requires-Dist: typing (==3.10.0.0) ; python_version < "3.5"
